MANIFEST.in
README.rst
setup.py
byro_mailman/__init__.py
byro_mailman/models.py
byro_mailman/signals.py
byro_mailman/urls.py
byro_mailman/views.py
byro_mailman.egg-info/PKG-INFO
byro_mailman.egg-info/SOURCES.txt
byro_mailman.egg-info/dependency_links.txt
byro_mailman.egg-info/entry_points.txt
byro_mailman.egg-info/requires.txt
byro_mailman.egg-info/top_level.txt
byro_mailman/locale/de/LC_MESSAGES/django.po
byro_mailman/migrations/0001_initial.py
byro_mailman/migrations/0002_auto_20180326_2141.py
byro_mailman/migrations/__init__.py
byro_mailman/static/byro_mailman/.gitkeep
byro_mailman/templates/byro_mailman/.gitkeep
byro_mailman/templates/byro_mailman/mailman.html
byro_mailman/templates/byro_mailman/member_lists.html