Metadata-Version: 1.0
Name: byro-mailman
Version: 1.0.1
Summary: Mailing list integration for byro
Home-page: https://github.com/byro/byro-mailman
Author: rixx
Author-email: r@rixx.de
License: Apache Software License
Platform: UNKNOWN
